gnow/__init__.py
gnow/check.py
gnow/color.py
gnow/command.py
gnow/main.py
gnow/test_func.py
gnow-1.0.1.dist-info/METADATA
gnow-1.0.1.dist-info/WHEEL
gnow-1.0.1.dist-info/entry_points.txt
gnow-1.0.1.dist-info/top_level.txt
gnow-1.0.1.dist-info/RECORD
