Metadata-Version: 2.1
Name: gnow
Version: 1.0.1
Summary: This command makes it easy to git add / commit /push and auto-increment tagging.
Home-page: https://github.com/addshlab/gnow
Author: addshlab
License: MIT
Keywords: git
Platform: UNKNOWN
Classifier: Topic :: Software Development :: Version Control :: Git
Classifier: Programming Language :: Python :: 3
Classifier: Programming Language :: Python :: 3.9
Classifier: Programming Language :: Python :: 3.8
Classifier: Programming Language :: Python :: 3.7
Classifier: Programming Language :: Python :: 3.6
Classifier: Programming Language :: Python :: 3.5
Classifier: License :: OSI Approved :: MIT License
